alembic/__init__.py
alembic/command.py
alembic/config.py
alembic/context.py
alembic/op.py
alembic/autogenerate/__init__.py
alembic/autogenerate/api.py
alembic/autogenerate/compare.py
alembic/autogenerate/render.py
alembic/autogenerate/rewriter.py
alembic/ddl/__init__.py
alembic/ddl/base.py
alembic/ddl/impl.py
alembic/ddl/mssql.py
alembic/ddl/mysql.py
alembic/ddl/oracle.py
alembic/ddl/postgresql.py
alembic/ddl/sqlite.py
alembic/operations/__init__.py
alembic/operations/base.py
alembic/operations/batch.py
alembic/operations/ops.py
alembic/operations/schemaobj.py
alembic/operations/toimpl.py
alembic/runtime/__init__.py
alembic/runtime/environment.py
alembic/runtime/migration.py
alembic/script/__init__.py
alembic/script/base.py
alembic/script/revision.py
alembic/script/write_hooks.py
alembic/templates/generic/README
alembic/templates/generic/alembic.ini.mako
alembic/templates/generic/env.py
alembic/templates/generic/script.py.mako
alembic/templates/multidb/README
alembic/templates/multidb/alembic.ini.mako
alembic/templates/multidb/env.py
alembic/templates/multidb/script.py.mako
alembic/templates/pylons/README
alembic/templates/pylons/alembic.ini.mako
alembic/templates/pylons/env.py
alembic/templates/pylons/script.py.mako
alembic/testing/__init__.py
alembic/testing/assertions.py
alembic/testing/env.py
alembic/testing/exclusions.py
alembic/testing/fixture_functions.py
alembic/testing/fixtures.py
alembic/testing/requirements.py
alembic/testing/util.py
alembic/testing/plugin/__init__.py
alembic/testing/plugin/bootstrap.py
alembic/testing/plugin/plugin_base.py
alembic/testing/plugin/pytestplugin.py
alembic/util/__init__.py
alembic/util/compat.py
alembic/util/exc.py
alembic/util/langhelpers.py
alembic/util/messaging.py
alembic/util/pyfiles.py
alembic/util/sqla_compat.py
tiangolo_temp_alembic-1.4.3.dev0.dist-info/LICENSE
tiangolo_temp_alembic-1.4.3.dev0.dist-info/METADATA
tiangolo_temp_alembic-1.4.3.dev0.dist-info/WHEEL
tiangolo_temp_alembic-1.4.3.dev0.dist-info/entry_points.txt
tiangolo_temp_alembic-1.4.3.dev0.dist-info/top_level.txt
tiangolo_temp_alembic-1.4.3.dev0.dist-info/RECORD
