Metadata-Version: 2.1
Name: tiangolo-temp-alembic
Version: 1.4.3.dev0
Summary: A database migration tool for SQLAlchemy.
Home-page: https://alembic.sqlalchemy.org
Author: Mike Bayer
Author-email: mike@zzzcomputing.com
License: MIT
Project-URL: Issue Tracker, https://github.com/sqlalchemy/alembic/
Keywords: SQLAlchemy migrations
Platform: UNKNOWN
Classifier: Development Status :: 5 - Production/Stable
Classifier: Environment :: Console
Classifier: License :: OSI Approved :: MIT License
Classifier: Intended Audience :: Developers
Classifier: Programming Language :: Python
Classifier: Programming Language :: Python :: 2
Classifier: Programming Language :: Python :: 2.7
Classifier: Programming Language :: Python :: 3
Classifier: Programming Language :: Python :: 3.5
Classifier: Programming Language :: Python :: 3.6
Classifier: Programming Language :: Python :: 3.7
Classifier: Programming Language :: Python :: 3.8
Classifier: Programming Language :: Python :: Implementation :: CPython
Classifier: Programming Language :: Python :: Implementation :: PyPy
Classifier: Topic :: Database :: Front-Ends
Requires-Python: >=2.7, !=3.0.*, !=3.1.*, !=3.2.*, !=3.3.*
Requires-Dist: SQLAlchemy (>=1.1.0)
Requires-Dist: Mako
Requires-Dist: python-editor (>=0.3)
Requires-Dist: python-dateutil
